govuk_country_register/__init__.py
govuk_country_register/country.csv
govuk_country_register/country.py
govuk_country_register/register.py
govuk_country_register-0.5.0.dist-info/LICENSE.txt
govuk_country_register-0.5.0.dist-info/METADATA
govuk_country_register-0.5.0.dist-info/WHEEL
govuk_country_register-0.5.0.dist-info/top_level.txt
govuk_country_register-0.5.0.dist-info/RECORD
